kahi_siiu_projects/Kahi_siiu_projects.py
kahi_siiu_projects/__init__.py
kahi_siiu_projects/_version.py
kahi_siiu_projects/parser.py
kahi_siiu_projects/process_one.py
Kahi_siiu_projects-0.0.1a0.dist-info/METADATA
Kahi_siiu_projects-0.0.1a0.dist-info/WHEEL
Kahi_siiu_projects-0.0.1a0.dist-info/top_level.txt
Kahi_siiu_projects-0.0.1a0.dist-info/RECORD
