Metadata-Version: 2.2
Name: Kahi_siiu_projects
Version: 0.0.1a0
Summary: Kahi plugin to extract UdeA SIIU projects
Home-page: https://github.com/colav/Kahi_plugins
Author: Colav
Author-email: colav@udea.edu.co
License: BSD
Requires-Dist: kahi
Dynamic: author
Dynamic: author-email
Dynamic: description
Dynamic: description-content-type
Dynamic: home-page
Dynamic: license
Dynamic: requires-dist
Dynamic: summary
